{
  "generated_at": "2026-04-03T10:32:38.337550",
  "days_to_show": 13,
  "period_days": 7,
  "instagram": {
    "last_date": "2026-04-03",
    "followers": 5107,
    "reach": 6090,
    "accounts_engaged": 67,
    "followers_prev": 4906,
    "followers_change": 201,
    "followers_pct": 4.1,
    "period_posts": 3,
    "period_reach": 2476,
    "period_engagement": 200,
    "top_post": {
      "date": "2026-03-29",
      "type": "reel",
      "caption": "Un recorte de lo que vos digas \n\nLa versión también INcompleta está en YouTube \n",
      "reach": 1271
    },
    "trend": [
      {
        "date": "2026-03-04",
        "followers": 4246,
        "reach": 6321
      },
      {
        "date": "2026-03-05",
        "followers": 4276,
        "reach": 5315
      },
      {
        "date": "2026-03-06",
        "followers": 4311,
        "reach": 4275
      },
      {
        "date": "2026-03-07",
        "followers": 4352,
        "reach": 4980
      },
      {
        "date": "2026-03-08",
        "followers": 4387,
        "reach": 5208
      },
      {
        "date": "2026-03-09",
        "followers": 4422,
        "reach": 6496
      },
      {
        "date": "2026-03-10",
        "followers": 4477,
        "reach": 5360
      },
      {
        "date": "2026-03-11",
        "followers": 4513,
        "reach": 5951
      },
      {
        "date": "2026-03-12",
        "followers": 4530,
        "reach": 4165
      },
      {
        "date": "2026-03-13",
        "followers": 4567,
        "reach": 4607
      },
      {
        "date": "2026-03-14",
        "followers": 4594,
        "reach": 4391
      },
      {
        "date": "2026-03-15",
        "followers": 4595,
        "reach": 267
      },
      {
        "date": "2026-03-16",
        "followers": 4593,
        "reach": 1006
      },
      {
        "date": "2026-03-17",
        "followers": 4592,
        "reach": 690
      },
      {
        "date": "2026-03-18",
        "followers": 4598,
        "reach": 210
      },
      {
        "date": "2026-03-19",
        "followers": 4602,
        "reach": 1064
      },
      {
        "date": "2026-03-20",
        "followers": 4650,
        "reach": 7522
      },
      {
        "date": "2026-03-21",
        "followers": 4707,
        "reach": 8168
      },
      {
        "date": "2026-03-22",
        "followers": 4749,
        "reach": 7357
      },
      {
        "date": "2026-03-23",
        "followers": 4784,
        "reach": 4597
      },
      {
        "date": "2026-03-24",
        "followers": 4820,
        "reach": 4764
      },
      {
        "date": "2026-03-25",
        "followers": 4846,
        "reach": 7304
      },
      {
        "date": "2026-03-26",
        "followers": 4874,
        "reach": 6134
      },
      {
        "date": "2026-03-27",
        "followers": 4906,
        "reach": 5785
      },
      {
        "date": "2026-03-28",
        "followers": 4934,
        "reach": 5795
      },
      {
        "date": "2026-03-29",
        "followers": 4975,
        "reach": 4142
      },
      {
        "date": "2026-03-30",
        "followers": 4994,
        "reach": 7071
      },
      {
        "date": "2026-03-31",
        "followers": 5040,
        "reach": 7375
      },
      {
        "date": "2026-04-01",
        "followers": 5067,
        "reach": 4496
      },
      {
        "date": "2026-04-02",
        "followers": 5077,
        "reach": 6076
      },
      {
        "date": "2026-04-03",
        "followers": 5107,
        "reach": 6090
      }
    ],
    "post_types": [
      {
        "type": "reel",
        "posts": 5,
        "avg_reach": 1985.0,
        "avg_engagement": 170.0
      },
      {
        "type": "carousel",
        "posts": 3,
        "avg_reach": 1089.0,
        "avg_engagement": 97.0
      }
    ]
  },
  "email": {
    "last_date": "2026-04-01",
    "total_subs": 1669,
    "subs_prev": 1669,
    "subs_change": 0,
    "subs_pct": 0.0,
    "period_gained": 0,
    "period_lost": 525,
    "campaigns": [
      {
        "name": "Ya no saben qué decir - exclusivo lista del reencuentro",
        "sent": 583,
        "open_pct": 43.6,
        "click_pct": 8.6,
        "sent_at": "2026-02-27T14:05:14+00:00"
      },
      {
        "name": "Buscando Espacio - exclusivo lista del reencuentro",
        "sent": 503,
        "open_pct": 48.9,
        "click_pct": 11.7,
        "sent_at": "2026-02-20T17:33:54+00:00"
      },
      {
        "name": "Bienvenida a la lista",
        "sent": 503,
        "open_pct": 65.6,
        "click_pct": 22.7,
        "sent_at": "2026-02-13T12:21:59+00:00"
      }
    ],
    "last_campaign": {
      "name": "Ya no saben qué decir - exclusivo lista del reencuentro",
      "sent": 583,
      "open_pct": 43.6,
      "click_pct": 8.6,
      "sent_at": "2026-02-27T14:05:14+00:00"
    },
    "avg_open_pct": 52.7,
    "avg_click_pct": 14.3,
    "total_campaigns": 3,
    "trend": [
      {
        "date": "2026-03-04",
        "subs": 1553
      },
      {
        "date": "2026-03-05",
        "subs": 1553
      },
      {
        "date": "2026-03-06",
        "subs": 1552
      },
      {
        "date": "2026-03-07",
        "subs": 1550
      },
      {
        "date": "2026-03-08",
        "subs": 1550
      },
      {
        "date": "2026-03-09",
        "subs": 1550
      },
      {
        "date": "2026-03-10",
        "subs": 1550
      },
      {
        "date": "2026-03-11",
        "subs": 1549
      },
      {
        "date": "2026-03-12",
        "subs": 1549
      },
      {
        "date": "2026-03-13",
        "subs": 1549
      },
      {
        "date": "2026-03-14",
        "subs": 1549
      },
      {
        "date": "2026-03-15",
        "subs": 1549
      },
      {
        "date": "2026-03-16",
        "subs": 1675
      },
      {
        "date": "2026-03-17",
        "subs": 1670
      },
      {
        "date": "2026-03-18",
        "subs": 1670
      },
      {
        "date": "2026-03-19",
        "subs": 1670
      },
      {
        "date": "2026-03-20",
        "subs": 1670
      },
      {
        "date": "2026-03-21",
        "subs": 1670
      },
      {
        "date": "2026-03-22",
        "subs": 1670
      },
      {
        "date": "2026-03-23",
        "subs": 1670
      },
      {
        "date": "2026-03-25",
        "subs": 1669
      },
      {
        "date": "2026-03-29",
        "subs": 1669
      },
      {
        "date": "2026-03-30",
        "subs": 1669
      },
      {
        "date": "2026-04-01",
        "subs": 1669
      }
    ]
  },
  "youtube": {
    "last_date": "2026-04-02",
    "subscribers": 3790,
    "total_views": 1558565,
    "videos_count": 49,
    "subs_prev": 3790,
    "subs_change": 0,
    "subs_pct": 0.0,
    "period_views": 904,
    "period_likes": 22,
    "period_shares": 9,
    "period_watch_min": 2387.0,
    "period_subs_net": 2,
    "unreplied_comments": 11,
    "top_traffic_source": "PLAYLIST",
    "top_traffic_views": 15510,
    "traffic_sources": [
      {
        "source": "SHORTS",
        "views": 55380
      },
      {
        "source": "PLAYLIST",
        "views": 54572
      },
      {
        "source": "SUBSCRIBER",
        "views": 20120
      },
      {
        "source": "YT_SEARCH",
        "views": 18542
      },
      {
        "source": "RELATED_VIDEO",
        "views": 10398
      },
      {
        "source": "YT_CHANNEL",
        "views": 7627
      },
      {
        "source": "EXT_URL",
        "views": 5985
      },
      {
        "source": "NO_LINK_OTHER",
        "views": 5846
      },
      {
        "source": "YT_OTHER_PAGE",
        "views": 5790
      },
      {
        "source": "NOTIFICATION",
        "views": 2518
      },
      {
        "source": "SOUND_PAGE",
        "views": 39
      },
      {
        "source": "END_SCREEN",
        "views": 22
      },
      {
        "source": "SHORTS_CONTENT_LINKS",
        "views": 14
      }
    ],
    "top_videos": [
      {
        "title": "LA SAGA -  \"Color\" - (Video Oficial)",
        "views": 501257,
        "likes": 2238,
        "type": "Video"
      },
      {
        "title": "LA SAGA - ONCE",
        "views": 467877,
        "likes": 2344,
        "type": "Video"
      },
      {
        "title": "\"Errante\" (La Saga - \"INTIMO\")",
        "views": 162375,
        "likes": 700,
        "type": "Video"
      },
      {
        "title": "La Saga - Yo te quiero (Video Oficial)",
        "views": 116305,
        "likes": 689,
        "type": "Video"
      },
      {
        "title": "La Saga - Vos  (video oficial)",
        "views": 107170,
        "likes": 869,
        "type": "Video"
      }
    ],
    "trend": [
      {
        "date": "2026-03-04",
        "views": 271,
        "likes": 2,
        "net_subs": 0
      },
      {
        "date": "2026-03-05",
        "views": 298,
        "likes": 7,
        "net_subs": 0
      },
      {
        "date": "2026-03-06",
        "views": 240,
        "likes": 1,
        "net_subs": 0
      },
      {
        "date": "2026-03-07",
        "views": 232,
        "likes": 3,
        "net_subs": 0
      },
      {
        "date": "2026-03-08",
        "views": 231,
        "likes": 1,
        "net_subs": 3
      },
      {
        "date": "2026-03-09",
        "views": 225,
        "likes": -2,
        "net_subs": 0
      },
      {
        "date": "2026-03-10",
        "views": 308,
        "likes": 4,
        "net_subs": 6
      },
      {
        "date": "2026-03-11",
        "views": 220,
        "likes": 1,
        "net_subs": 2
      },
      {
        "date": "2026-03-12",
        "views": 192,
        "likes": 2,
        "net_subs": 0
      },
      {
        "date": "2026-03-13",
        "views": 254,
        "likes": 3,
        "net_subs": 1
      },
      {
        "date": "2026-03-14",
        "views": 276,
        "likes": 4,
        "net_subs": 0
      },
      {
        "date": "2026-03-15",
        "views": 330,
        "likes": 30,
        "net_subs": 1
      },
      {
        "date": "2026-03-16",
        "views": 333,
        "likes": 9,
        "net_subs": 0
      },
      {
        "date": "2026-03-17",
        "views": 244,
        "likes": 2,
        "net_subs": 1
      },
      {
        "date": "2026-03-18",
        "views": 234,
        "likes": 5,
        "net_subs": 2
      },
      {
        "date": "2026-03-19",
        "views": 265,
        "likes": 11,
        "net_subs": -1
      },
      {
        "date": "2026-03-20",
        "views": 275,
        "likes": 4,
        "net_subs": 1
      },
      {
        "date": "2026-03-21",
        "views": 274,
        "likes": 1,
        "net_subs": 1
      },
      {
        "date": "2026-03-22",
        "views": 250,
        "likes": 16,
        "net_subs": 1
      },
      {
        "date": "2026-03-23",
        "views": 253,
        "likes": 5,
        "net_subs": -3
      },
      {
        "date": "2026-03-24",
        "views": 255,
        "likes": 3,
        "net_subs": 2
      },
      {
        "date": "2026-03-25",
        "views": 230,
        "likes": 2,
        "net_subs": 0
      },
      {
        "date": "2026-03-26",
        "views": 233,
        "likes": 0,
        "net_subs": 3
      },
      {
        "date": "2026-03-27",
        "views": 189,
        "likes": 1,
        "net_subs": 0
      },
      {
        "date": "2026-03-28",
        "views": 255,
        "likes": 4,
        "net_subs": 1
      },
      {
        "date": "2026-03-29",
        "views": 233,
        "likes": 15,
        "net_subs": 1
      },
      {
        "date": "2026-03-30",
        "views": 227,
        "likes": 2,
        "net_subs": 0
      }
    ]
  },
  "spotify": {
    "last_date": "2026-03-29",
    "monthly_listeners": 20433,
    "streams_28d": 94580,
    "followers": 11000,
    "super_listeners": 443,
    "saves": 842,
    "playlist_adds": 880,
    "listeners_prev": 20711,
    "listeners_change": -278,
    "listeners_pct": -1.3,
    "streams_prev": 94859,
    "streams_change": -279,
    "top_tracks": [
      {
        "name": "Color",
        "streams": 18747,
        "listeners": 11077,
        "saves": 133
      },
      {
        "name": "Once",
        "streams": 13411,
        "listeners": 7903,
        "saves": 81
      },
      {
        "name": "Ir",
        "streams": 8844,
        "listeners": 5385,
        "saves": 60
      },
      {
        "name": "Vos",
        "streams": 7118,
        "listeners": 4480,
        "saves": 42
      },
      {
        "name": "De Cabeza",
        "streams": 5301,
        "listeners": 3152,
        "saves": 47
      },
      {
        "name": "Errante",
        "streams": 5289,
        "listeners": 3246,
        "saves": 30
      },
      {
        "name": "Buscando Espacio (Un Lugar)",
        "streams": 4920,
        "listeners": 2847,
        "saves": 38
      },
      {
        "name": "El Grito del León",
        "streams": 2947,
        "listeners": 1884,
        "saves": 12
      },
      {
        "name": "Estoy Perdido",
        "streams": 2561,
        "listeners": 1717,
        "saves": 15
      },
      {
        "name": "Contrario",
        "streams": 2542,
        "listeners": 1642,
        "saves": 17
      }
    ],
    "demographics": [
      {
        "dim": "age",
        "value": "35-44",
        "pct": 36.0
      },
      {
        "dim": "age",
        "value": "25-34",
        "pct": 33.0
      },
      {
        "dim": "age",
        "value": "45-54",
        "pct": 18.0
      },
      {
        "dim": "age",
        "value": "18-24",
        "pct": 6.0
      },
      {
        "dim": "age",
        "value": "55-64",
        "pct": 5.0
      },
      {
        "dim": "age",
        "value": "65+",
        "pct": 2.0
      },
      {
        "dim": "age",
        "value": "<18",
        "pct": 0.0
      },
      {
        "dim": "gender",
        "value": "male",
        "pct": 63.0
      },
      {
        "dim": "gender",
        "value": "female",
        "pct": 33.0
      },
      {
        "dim": "gender",
        "value": "not_specified",
        "pct": 3.0
      },
      {
        "dim": "gender",
        "value": "non-binary",
        "pct": 1.0
      }
    ],
    "locations": [
      {
        "name": "Uruguay",
        "listeners": 13565
      },
      {
        "name": "Argentina",
        "listeners": 4152
      },
      {
        "name": "Spain",
        "listeners": 823
      },
      {
        "name": "Mexico",
        "listeners": 437
      },
      {
        "name": "Brazil",
        "listeners": 239
      }
    ],
    "days_since_collection": 5,
    "trend": [
      {
        "date": "2026-02-18",
        "listeners": 21909,
        "streams": 100745,
        "followers": 11261
      },
      {
        "date": "2026-02-20",
        "listeners": 22018,
        "streams": 99935,
        "followers": 11268
      },
      {
        "date": "2026-02-26",
        "listeners": 22710,
        "streams": 98784,
        "followers": 11000
      },
      {
        "date": "2026-02-27",
        "listeners": 22597,
        "streams": 98231,
        "followers": 11297
      },
      {
        "date": "2026-03-01",
        "listeners": 22661,
        "streams": 99055,
        "followers": 11302
      },
      {
        "date": "2026-03-02",
        "listeners": 22584,
        "streams": 98959,
        "followers": 11306
      },
      {
        "date": "2026-03-04",
        "listeners": 22635,
        "streams": 99048,
        "followers": 11312
      },
      {
        "date": "2026-03-05",
        "listeners": 22799,
        "streams": 99431,
        "followers": 11314
      },
      {
        "date": "2026-03-06",
        "listeners": 22737,
        "streams": 98944,
        "followers": 11000
      },
      {
        "date": "2026-03-07",
        "listeners": 22591,
        "streams": 98024,
        "followers": 11319
      },
      {
        "date": "2026-03-08",
        "listeners": 22373,
        "streams": 96984,
        "followers": 11000
      },
      {
        "date": "2026-03-09",
        "listeners": 22261,
        "streams": 96791,
        "followers": 11334
      },
      {
        "date": "2026-03-10",
        "listeners": 22167,
        "streams": 96545,
        "followers": 11000
      },
      {
        "date": "2026-03-11",
        "listeners": 22121,
        "streams": 96653,
        "followers": 11000
      },
      {
        "date": "2026-03-13",
        "listeners": 22294,
        "streams": 97626,
        "followers": 11349
      },
      {
        "date": "2026-03-14",
        "listeners": 22159,
        "streams": 97011,
        "followers": 11354
      },
      {
        "date": "2026-03-15",
        "listeners": 22159,
        "streams": 97011,
        "followers": 11000
      },
      {
        "date": "2026-03-16",
        "listeners": 21851,
        "streams": 96000,
        "followers": 11000
      },
      {
        "date": "2026-03-17",
        "listeners": 21582,
        "streams": 95557,
        "followers": 11000
      },
      {
        "date": "2026-03-18",
        "listeners": 21332,
        "streams": 95096,
        "followers": 11367
      },
      {
        "date": "2026-03-19",
        "listeners": 21187,
        "streams": 95050,
        "followers": 11000
      },
      {
        "date": "2026-03-20",
        "listeners": 21156,
        "streams": 95402,
        "followers": 11000
      },
      {
        "date": "2026-03-21",
        "listeners": 21159,
        "streams": 95545,
        "followers": 11000
      },
      {
        "date": "2026-03-22",
        "listeners": 21107,
        "streams": 95245,
        "followers": 11000
      },
      {
        "date": "2026-03-23",
        "listeners": 20711,
        "streams": 94859,
        "followers": 11383
      },
      {
        "date": "2026-03-24",
        "listeners": 20711,
        "streams": 94859,
        "followers": 11383
      },
      {
        "date": "2026-03-29",
        "listeners": 20433,
        "streams": 94580,
        "followers": 11000
      }
    ]
  },
  "x": {
    "last_date": "2026-04-02",
    "followers": 1380,
    "following": 504,
    "followers_prev": 1380,
    "top_posts": [
      {
        "post_id": "2024191756430884898",
        "date": "2026-02-18",
        "text": "#lasagavuelve [imagen]",
        "impressions": 217,
        "likes": 17,
        "retweets": 3,
        "bookmarks": 0,
        "replies": 1
      },
      {
        "post_id": "2024536551791759399",
        "date": "2026-02-19",
        "text": "Pregunta para los que nos escuchan desde siempre: ¿qué tema de La Saga les gusta",
        "impressions": 286,
        "likes": 5,
        "retweets": 0,
        "bookmarks": 0,
        "replies": 10
      },
      {
        "post_id": "1067231560431210496",
        "date": "2018-11-26",
        "text": "¿Quien tiene ganas de despedida?",
        "impressions": 0,
        "likes": 8,
        "retweets": 2,
        "bookmarks": 0,
        "replies": 0
      },
      {
        "post_id": "2027443387947688068",
        "date": "2026-02-27",
        "text": "Ya no saben que decir — tema de Buitres, grabado por La Saga. Parece despedida p",
        "impressions": 370,
        "likes": 7,
        "retweets": 1,
        "bookmarks": 0,
        "replies": 0
      },
      {
        "post_id": "2034806026059268122",
        "date": "2026-03-19",
        "text": "Escuchando, un día nos encontramos tocando. #influencias @LASAGArock @LaVela_Ofi",
        "impressions": 334,
        "likes": 5,
        "retweets": 2,
        "bookmarks": 0,
        "replies": 0
      }
    ],
    "trend": [
      {
        "date": "2026-03-04",
        "followers": 1367
      },
      {
        "date": "2026-03-05",
        "followers": 1368
      },
      {
        "date": "2026-03-06",
        "followers": 1370
      },
      {
        "date": "2026-03-07",
        "followers": 1369
      },
      {
        "date": "2026-03-08",
        "followers": 1369
      },
      {
        "date": "2026-03-09",
        "followers": 1371
      },
      {
        "date": "2026-03-10",
        "followers": 1372
      },
      {
        "date": "2026-03-11",
        "followers": 1373
      },
      {
        "date": "2026-03-12",
        "followers": 1375
      },
      {
        "date": "2026-03-13",
        "followers": 1375
      },
      {
        "date": "2026-03-14",
        "followers": 1375
      },
      {
        "date": "2026-03-15",
        "followers": 1376
      },
      {
        "date": "2026-03-16",
        "followers": 1378
      },
      {
        "date": "2026-03-17",
        "followers": 1378
      },
      {
        "date": "2026-03-18",
        "followers": 1378
      },
      {
        "date": "2026-03-19",
        "followers": 1378
      },
      {
        "date": "2026-03-21",
        "followers": 1379
      },
      {
        "date": "2026-03-22",
        "followers": 1379
      },
      {
        "date": "2026-03-23",
        "followers": 1379
      },
      {
        "date": "2026-03-24",
        "followers": 1379
      },
      {
        "date": "2026-03-26",
        "followers": 1380
      },
      {
        "date": "2026-03-28",
        "followers": 1380
      },
      {
        "date": "2026-03-29",
        "followers": 1380
      },
      {
        "date": "2026-03-30",
        "followers": 1380
      },
      {
        "date": "2026-03-31",
        "followers": 1380
      },
      {
        "date": "2026-04-01",
        "followers": 1380
      },
      {
        "date": "2026-04-02",
        "followers": 1380
      }
    ]
  },
  "community": {
    "platforms": {
      "instagram": {
        "comments_received": 64,
        "comments_replied": 10,
        "dms_received": 11,
        "dms_replied": 8,
        "mentions_received": 0,
        "mentions_replied": 0,
        "likes_given": 23,
        "response_time_avg_min": 0
      },
      "youtube": {
        "comments_received": 43,
        "comments_replied": 11,
        "dms_received": 0,
        "dms_replied": 0,
        "mentions_received": 0,
        "mentions_replied": 0,
        "likes_given": 4,
        "response_time_avg_min": 0
      }
    },
    "total_received": 118,
    "total_replied": 29,
    "response_rate": 25,
    "total_likes": 27,
    "today_grid": [
      {
        "platform": "instagram",
        "shift": "AM",
        "received": 11,
        "replied": 7,
        "pending": 3
      },
      {
        "platform": "youtube",
        "shift": "AM",
        "received": 0,
        "replied": 0,
        "pending": 0
      }
    ],
    "trend": [
      {
        "date": "2026-03-04",
        "received": 23,
        "replied": 18
      },
      {
        "date": "2026-03-05",
        "received": 8,
        "replied": 7
      },
      {
        "date": "2026-03-06",
        "received": 7,
        "replied": 3
      },
      {
        "date": "2026-03-07",
        "received": 36,
        "replied": 15
      },
      {
        "date": "2026-03-08",
        "received": 27,
        "replied": 14
      },
      {
        "date": "2026-03-09",
        "received": 26,
        "replied": 17
      },
      {
        "date": "2026-03-10",
        "received": 25,
        "replied": 11
      },
      {
        "date": "2026-03-11",
        "received": 31,
        "replied": 17
      },
      {
        "date": "2026-03-12",
        "received": 23,
        "replied": 15
      },
      {
        "date": "2026-03-13",
        "received": 24,
        "replied": 16
      },
      {
        "date": "2026-03-14",
        "received": 3,
        "replied": 1
      },
      {
        "date": "2026-03-15",
        "received": 8,
        "replied": 5
      },
      {
        "date": "2026-03-16",
        "received": 4,
        "replied": 1
      },
      {
        "date": "2026-03-17",
        "received": 12,
        "replied": 7
      },
      {
        "date": "2026-03-18",
        "received": 8,
        "replied": 5
      },
      {
        "date": "2026-03-19",
        "received": 21,
        "replied": 12
      },
      {
        "date": "2026-03-20",
        "received": 18,
        "replied": 12
      },
      {
        "date": "2026-03-21",
        "received": 18,
        "replied": 9
      },
      {
        "date": "2026-03-22",
        "received": 12,
        "replied": 4
      },
      {
        "date": "2026-03-23",
        "received": 6,
        "replied": 0
      },
      {
        "date": "2026-03-24",
        "received": 7,
        "replied": 1
      },
      {
        "date": "2026-03-25",
        "received": 7,
        "replied": 1
      },
      {
        "date": "2026-03-26",
        "received": 17,
        "replied": 3
      },
      {
        "date": "2026-03-27",
        "received": 3,
        "replied": 0
      },
      {
        "date": "2026-03-28",
        "received": 28,
        "replied": 2
      },
      {
        "date": "2026-03-29",
        "received": 23,
        "replied": 6
      },
      {
        "date": "2026-03-30",
        "received": 21,
        "replied": 7
      },
      {
        "date": "2026-03-31",
        "received": 16,
        "replied": 4
      },
      {
        "date": "2026-04-01",
        "received": 11,
        "replied": 1
      },
      {
        "date": "2026-04-02",
        "received": 5,
        "replied": 2
      },
      {
        "date": "2026-04-03",
        "received": 11,
        "replied": 7
      }
    ]
  },
  "community_log": [
    {
      "date": "2026-04-01",
      "platform": "youtube",
      "type": "scan",
      "description": "PM scan: 608 threads, 0 unreplied"
    },
    {
      "date": "2026-03-31",
      "platform": "youtube",
      "type": "reply",
      "description": "@FABRI19022 en ONCE - elogio a música uruguaya"
    },
    {
      "date": "2026-03-31",
      "platform": "youtube",
      "type": "reply",
      "description": "@veckemorales3792 en Color - transcribió letra completa"
    },
    {
      "date": "2026-03-31",
      "platform": "youtube",
      "type": "reply",
      "description": "@andreseduardo600 en Estoy perdido - humor sobre baterista"
    },
    {
      "date": "2026-03-30",
      "platform": "youtube",
      "type": "like",
      "description": "Corazón a @thetacogaming9434, @andreseduardo600, @ghostzerosniperpsp en Estoy perdido y @jimenezromanomarnadin9627 en Lo que vos digas"
    },
    {
      "date": "2026-03-30",
      "platform": "youtube",
      "type": "reply",
      "description": "Respondido @FABRI19022 en ONCE - agradecimiento por valorar música uruguaya"
    },
    {
      "date": "2026-03-30",
      "platform": "youtube",
      "type": "reply",
      "description": "Respondido @veckemorales3792 en Color - agradecimiento por transcribir letra"
    },
    {
      "date": "2026-03-30",
      "platform": "youtube",
      "type": "reply",
      "description": "AM: 3 replies (baterista humor, lyrics Color, Uruguay music pride). 2 pendientes por ambiguos (mencionan Max samson)."
    },
    {
      "date": "2026-03-29",
      "platform": "youtube",
      "type": "reply",
      "description": "Replied to 3 comments on Estoy perdido, Color, and ONCE. 2 comments about Max not directed at band (skipped reply). Hearts blocked by YT Studio verification."
    },
    {
      "date": "2026-03-28",
      "platform": "youtube",
      "type": "audit",
      "description": "PM audit: 9 fan comments across all videos. 8/9 already responded (previous sessions). 1 pending escalated (@diariolateral entrevista). 2 hearts missing (@alfonsinapintos6122, @GabiCorboFotografo) - blocked by Google verification dialog. No new comments since AM."
    },
    {
      "date": "2026-03-28",
      "platform": "youtube",
      "type": "scan",
      "description": "AM scan: 7 comentarios visibles, todos ya respondidos previamente excepto @diariolateral (pedido de entrevista, escalado a Nicolás). Verificación de Google bloqueó interacción."
    },
    {
      "date": "2026-03-25",
      "platform": "youtube",
      "type": "scan",
      "description": "PM scan: revisados 5 videos recientes (Ir acústico, Eso que nos lleva, Errante, Ya no saben qué decir, Buscando Espacio). Todos los comentarios tienen corazón y respuesta. @diariolateral pendiente (escalado AM)."
    },
    {
      "date": "2026-03-25",
      "platform": "youtube",
      "type": "heart",
      "description": "Corazón a @diariolateral, @claualbirrojo, @faradar2457 en Ir"
    },
    {
      "date": "2026-03-25",
      "platform": "youtube",
      "type": "reply",
      "description": "Respondido @donarildo en Color con agradecimiento + corazón"
    },
    {
      "date": "2026-03-24",
      "platform": "youtube",
      "type": "scan",
      "description": "PM scan: 7 total comments on Ir video. 4 top-level visible. 3 already replied by us (claualbirrojo, marcedl1989, faradar2457). 1 pending Nicolás (diariolateral - entrevista request, reported AM). 0 new comments since AM. Studio blocked by Google verification - cannot give hearts."
    }
  ],
  "suggestions": [
    {
      "priority": "alta",
      "area": "Comunidad",
      "text": "Tasa de respuesta en 25%. Objetivo: >80%. Aumentar rondas de comunidad."
    }
  ],
  "press": {
    "total_contacts": 19,
    "emails_sent": 6,
    "responses": 4,
    "coverage": 1,
    "recent_activity": [
      {
        "date": "2026-03-31",
        "contact": "Belén Fourment",
        "outlet": "El País / Canal 4",
        "sent": 0,
        "response": 0,
        "published": 0,
        "url": ""
      },
      {
        "date": "2026-03-31",
        "contact": "Javier Alfonso",
        "outlet": "Búsqueda",
        "sent": 0,
        "response": 0,
        "published": 0,
        "url": ""
      },
      {
        "date": "2026-03-31",
        "contact": "Nelson Barceló",
        "outlet": "Emisora del Sur",
        "sent": 0,
        "response": 0,
        "published": 0,
        "url": ""
      },
      {
        "date": "2026-03-28",
        "contact": "",
        "outlet": "Independiente",
        "sent": 1,
        "response": 0,
        "published": 0,
        "url": ""
      },
      {
        "date": "2026-03-28",
        "contact": "",
        "outlet": "Productor Sala del Museo",
        "sent": 1,
        "response": 0,
        "published": 0,
        "url": ""
      },
      {
        "date": "2026-03-24",
        "contact": "Ariel Scarpa",
        "outlet": "Solo Rock Uruguay",
        "sent": 1,
        "response": 1,
        "published": 0,
        "url": ""
      },
      {
        "date": "2026-03-24",
        "contact": "Gustavo Cedrés",
        "outlet": "Rock Uruguayo Podcast",
        "sent": 1,
        "response": 1,
        "published": 0,
        "url": ""
      },
      {
        "date": "2026-03-24",
        "contact": "Valentín (Sala Corchea)",
        "outlet": "Produccion Fans / Sala Corchea",
        "sent": 1,
        "response": 1,
        "published": 0,
        "url": ""
      },
      {
        "date": "2026-03-17",
        "contact": "La Galera del Rock (Gastón Gómez)",
        "outlet": "La Caverna FM 90.7",
        "sent": 0,
        "response": 0,
        "published": 0,
        "url": ""
      },
      {
        "date": "2026-03-10",
        "contact": "Rock Uruguayo Podcast",
        "outlet": "Podcast YT/Spotify",
        "sent": 0,
        "response": 0,
        "published": 0,
        "url": ""
      }
    ],
    "trend": [
      {
        "date": "2026-02-26",
        "sent": 0,
        "responses": 0,
        "coverage": 0
      },
      {
        "date": "2026-03-01",
        "sent": 1,
        "responses": 1,
        "coverage": 1
      },
      {
        "date": "2026-03-02",
        "sent": 1,
        "responses": 1,
        "coverage": 1
      },
      {
        "date": "2026-03-03",
        "sent": 1,
        "responses": 1,
        "coverage": 1
      },
      {
        "date": "2026-03-04",
        "sent": 1,
        "responses": 1,
        "coverage": 1
      },
      {
        "date": "2026-03-05",
        "sent": 1,
        "responses": 1,
        "coverage": 1
      },
      {
        "date": "2026-03-06",
        "sent": 1,
        "responses": 1,
        "coverage": 1
      },
      {
        "date": "2026-03-07",
        "sent": 1,
        "responses": 1,
        "coverage": 1
      },
      {
        "date": "2026-03-08",
        "sent": 1,
        "responses": 1,
        "coverage": 1
      },
      {
        "date": "2026-03-09",
        "sent": 1,
        "responses": 1,
        "coverage": 1
      },
      {
        "date": "2026-03-10",
        "sent": 1,
        "responses": 1,
        "coverage": 1
      },
      {
        "date": "2026-03-11",
        "sent": 1,
        "responses": 1,
        "coverage": 1
      },
      {
        "date": "2026-03-12",
        "sent": 1,
        "responses": 1,
        "coverage": 1
      },
      {
        "date": "2026-03-13",
        "sent": 1,
        "responses": 1,
        "coverage": 1
      },
      {
        "date": "2026-03-14",
        "sent": 1,
        "responses": 1,
        "coverage": 1
      },
      {
        "date": "2026-03-15",
        "sent": 1,
        "responses": 1,
        "coverage": 1
      },
      {
        "date": "2026-03-16",
        "sent": 1,
        "responses": 1,
        "coverage": 1
      },
      {
        "date": "2026-03-17",
        "sent": 1,
        "responses": 1,
        "coverage": 1
      },
      {
        "date": "2026-03-18",
        "sent": 1,
        "responses": 1,
        "coverage": 1
      },
      {
        "date": "2026-03-19",
        "sent": 1,
        "responses": 1,
        "coverage": 1
      },
      {
        "date": "2026-03-20",
        "sent": 1,
        "responses": 1,
        "coverage": 1
      },
      {
        "date": "2026-03-21",
        "sent": 1,
        "responses": 1,
        "coverage": 1
      },
      {
        "date": "2026-03-22",
        "sent": 1,
        "responses": 1,
        "coverage": 1
      },
      {
        "date": "2026-03-23",
        "sent": 1,
        "responses": 1,
        "coverage": 1
      },
      {
        "date": "2026-03-24",
        "sent": 4,
        "responses": 4,
        "coverage": 1
      },
      {
        "date": "2026-03-25",
        "sent": 4,
        "responses": 4,
        "coverage": 1
      },
      {
        "date": "2026-03-26",
        "sent": 4,
        "responses": 4,
        "coverage": 1
      },
      {
        "date": "2026-03-27",
        "sent": 4,
        "responses": 4,
        "coverage": 1
      },
      {
        "date": "2026-03-28",
        "sent": 6,
        "responses": 4,
        "coverage": 1
      },
      {
        "date": "2026-03-29",
        "sent": 6,
        "responses": 4,
        "coverage": 1
      },
      {
        "date": "2026-03-30",
        "sent": 6,
        "responses": 4,
        "coverage": 1
      },
      {
        "date": "2026-03-31",
        "sent": 6,
        "responses": 4,
        "coverage": 1
      },
      {
        "date": "2026-04-01",
        "sent": 6,
        "responses": 4,
        "coverage": 1
      },
      {
        "date": "2026-04-02",
        "sent": 6,
        "responses": 4,
        "coverage": 1
      },
      {
        "date": "2026-04-03",
        "sent": 6,
        "responses": 4,
        "coverage": 1
      }
    ]
  },
  "booking": {
    "venues": [
      {
        "name": "Sala del Museo del Carnaval",
        "city": "Montevideo",
        "capacity": 0,
        "date_target": "Agosto/Septiembre 2026",
        "status": "researched",
        "contacted": null,
        "notes": "Gestiona: Producciones Doble Cinco (@doblecinco_producciones IG, @saladelmuseo IG 67K). Cap 1100 (pie), 650 o 350 reducida. Artistas previos: Vela Puerca, La Beriso, Buenos Muchachos, Las Pelotas, SKAY. Email protegido por JS. Contactar via IG @doblecinco_producciones o email museodelcarnaval.org. Borrador de email listo, requiere OK Nico."
      },
      {
        "name": "Wannaclap",
        "city": "Montevideo",
        "capacity": 0,
        "date_target": "17 Abril 2026",
        "status": "confirmed",
        "contacted": null,
        "notes": "Show principal La Saga Vuelve"
      },
      {
        "name": "Avril Festival",
        "city": "Montevideo",
        "capacity": 3000,
        "date_target": "Oct 2026",
        "status": "identified",
        "contacted": "",
        "notes": "Festival de rock nacional 18 oct 2026. Transmisión Under TV. Apoyo La Diaria, Let's Rock & Metal, Municipio B."
      },
      {
        "name": "La Trastienda MVD",
        "city": "Montevideo",
        "capacity": 700,
        "date_target": "2do sem 2026",
        "status": "identified",
        "contacted": "",
        "notes": "Cap ~780. Dir: Daniel Fernández Crespo 1763. Contacto via formulario web latrastiendamvd.com.uy. IG: @latrastiendamvd. No publican email/tel directo."
      },
      {
        "name": "Montevideo Music Box",
        "city": "Montevideo",
        "capacity": 1500,
        "date_target": "2do sem 2026",
        "status": "identified",
        "contacted": "",
        "notes": "Venue rock activo. W.A.S.P., Paradise Lost, Kerry King, Saxon en 2026. Email: contacto@montevideomusicbox.com.uy Tel: +598 2484 0712. Av. Dámaso A. Larrañaga 3195."
      },
      {
        "name": "Cosquin Rock Uruguay 2027",
        "city": "Montevideo",
        "capacity": 15000,
        "date_target": "Mar 2027",
        "status": "identified",
        "contacted": "",
        "notes": "2026 ya confirmado (21/3). Apuntar a edición 2027."
      },
      {
        "name": "Mercado Uruguay Musical",
        "city": "Montevideo",
        "capacity": 0,
        "date_target": "2do sem 2026",
        "status": "identified",
        "contacted": "",
        "notes": "Feria de industria musical. Networking + showcase. Ver mercadodemusica.uy para convocatoria."
      },
      {
        "name": "Festival de Durazno 2027",
        "city": "Durazno",
        "capacity": 20000,
        "date_target": "Ene/Feb 2027",
        "status": "identified",
        "contacted": "",
        "notes": "Festival municipal grande. Apuntar a edición 2027."
      },
      {
        "name": "Sala Zitarrosa",
        "city": "Montevideo",
        "capacity": 400,
        "date_target": "2do sem 2026",
        "status": "identified",
        "contacted": "",
        "notes": ""
      }
    ],
    "by_status": {
      "researched": 1,
      "confirmed": 1,
      "identified": 7
    },
    "total": 9
  },
  "upcoming": {
    "items": [
      {
        "id": 17,
        "date": "2026-03-29",
        "platform": "YouTube",
        "type": "Canción completa",
        "description": "Lo que vos digas — canción completa YouTube",
        "status": "published",
        "platforms_done": [
          "youtube",
          "x"
        ]
      },
      {
        "id": 18,
        "date": "2026-03-31",
        "platform": "IG/TikTok/YT Shorts",
        "type": "Estribillo",
        "description": "Estribillo de Lo que vos digas — reel vertical (pendiente corte + aprobación)",
        "status": "published",
        "platforms_done": []
      },
      {
        "id": 19,
        "date": "2026-04-02",
        "platform": "IG/TikTok/YT Shorts",
        "type": "Short",
        "description": "S6 El disco triste — anticipa Color",
        "status": "published",
        "platforms_done": []
      },
      {
        "id": 20,
        "date": "2026-04-04",
        "platform": "IG Feed",
        "type": "Carrusel",
        "description": "Carrusel de Color — imagen+frase (pendiente Nico)",
        "status": "planned",
        "platforms_done": []
      },
      {
        "id": 21,
        "date": "2026-04-05",
        "platform": "YouTube",
        "type": "Canción completa",
        "description": "Color — canción completa YouTube",
        "status": "planned",
        "platforms_done": []
      }
    ],
    "source": "upcoming_content"
  },
  "financials": {
    "total_expenses": 0,
    "total_income": 0,
    "balance": 0
  },
  "show": {
    "venue": "Wannaclap",
    "capacity": 0,
    "tickets_sold": 0,
    "revenue": 0.0,
    "status": "confirmed"
  },
  "kpi_history": [
    {
      "date": "2026-02-18",
      "total_followers": 18547,
      "total_reach": 6508,
      "total_engagement": 675,
      "email_list_size": 1635,
      "tickets_sold_total": 0
    },
    {
      "date": "2026-02-19",
      "total_followers": 7296,
      "total_reach": 5898,
      "total_engagement": 480,
      "email_list_size": 1635,
      "tickets_sold_total": 0
    },
    {
      "date": "2026-02-20",
      "total_followers": 18564,
      "total_reach": 6194,
      "total_engagement": 533,
      "email_list_size": 1635,
      "tickets_sold_total": 0
    },
    {
      "date": "2026-02-26",
      "total_followers": 18716,
      "total_reach": 3983,
      "total_engagement": 686,
      "email_list_size": 1663,
      "tickets_sold_total": 0
    },
    {
      "date": "2026-02-27",
      "total_followers": 19045,
      "total_reach": 3514,
      "total_engagement": 642,
      "email_list_size": 1715,
      "tickets_sold_total": 0
    },
    {
      "date": "2026-02-28",
      "total_followers": 19089,
      "total_reach": 5027,
      "total_engagement": 779,
      "email_list_size": 1715,
      "tickets_sold_total": 0
    },
    {
      "date": "2026-03-01",
      "total_followers": 19182,
      "total_reach": 4551,
      "total_engagement": 445,
      "email_list_size": 1558,
      "tickets_sold_total": 0
    },
    {
      "date": "2026-03-02",
      "total_followers": 19229,
      "total_reach": 5825,
      "total_engagement": 513,
      "email_list_size": 1558,
      "tickets_sold_total": 0
    },
    {
      "date": "2026-03-03",
      "total_followers": 19260,
      "total_reach": 6628,
      "total_engagement": 526,
      "email_list_size": 1553,
      "tickets_sold_total": 0
    },
    {
      "date": "2026-03-05",
      "total_followers": 19360,
      "total_reach": 8355,
      "total_engagement": 705,
      "email_list_size": 1553,
      "tickets_sold_total": 0
    },
    {
      "date": "2026-03-06",
      "total_followers": 19081,
      "total_reach": 6219,
      "total_engagement": 437,
      "email_list_size": 1552,
      "tickets_sold_total": 0
    },
    {
      "date": "2026-03-07",
      "total_followers": 19441,
      "total_reach": 3847,
      "total_engagement": 246,
      "email_list_size": 1550,
      "tickets_sold_total": 0
    },
    {
      "date": "2026-03-08",
      "total_followers": 19157,
      "total_reach": 4275,
      "total_engagement": 364,
      "email_list_size": 1550,
      "tickets_sold_total": 0
    },
    {
      "date": "2026-03-09",
      "total_followers": 19526,
      "total_reach": 6390,
      "total_engagement": 553,
      "email_list_size": 1550,
      "tickets_sold_total": 0
    },
    {
      "date": "2026-03-10",
      "total_followers": 19257,
      "total_reach": 7195,
      "total_engagement": 609,
      "email_list_size": 1550,
      "tickets_sold_total": 0
    },
    {
      "date": "2026-03-11",
      "total_followers": 19293,
      "total_reach": 5406,
      "total_engagement": 423,
      "email_list_size": 1549,
      "tickets_sold_total": 0
    },
    {
      "date": "2026-03-12",
      "total_followers": 19310,
      "total_reach": 6032,
      "total_engagement": 438,
      "email_list_size": 1549,
      "tickets_sold_total": 0
    },
    {
      "date": "2026-03-13",
      "total_followers": 19696,
      "total_reach": 6672,
      "total_engagement": 519,
      "email_list_size": 1549,
      "tickets_sold_total": 0
    },
    {
      "date": "2026-03-14",
      "total_followers": 19728,
      "total_reach": 6659,
      "total_engagement": 542,
      "email_list_size": 1549,
      "tickets_sold_total": 0
    },
    {
      "date": "2026-03-15",
      "total_followers": 19375,
      "total_reach": 4744,
      "total_engagement": 368,
      "email_list_size": 1549,
      "tickets_sold_total": 0
    },
    {
      "date": "2026-03-16",
      "total_followers": 19373,
      "total_reach": 1306,
      "total_engagement": 108,
      "email_list_size": 1675,
      "tickets_sold_total": 0
    },
    {
      "date": "2026-03-17",
      "total_followers": 19372,
      "total_reach": 2035,
      "total_engagement": 128,
      "email_list_size": 1670,
      "tickets_sold_total": 0
    },
    {
      "date": "2026-03-18",
      "total_followers": 19755,
      "total_reach": 2088,
      "total_engagement": 154,
      "email_list_size": 1670,
      "tickets_sold_total": 0
    },
    {
      "date": "2026-03-19",
      "total_followers": 19392,
      "total_reach": 2949,
      "total_engagement": 240,
      "email_list_size": 1670,
      "tickets_sold_total": 0
    },
    {
      "date": "2026-03-20",
      "total_followers": 19440,
      "total_reach": 3657,
      "total_engagement": 274,
      "email_list_size": 1670,
      "tickets_sold_total": 0
    },
    {
      "date": "2026-03-21",
      "total_followers": 19497,
      "total_reach": 3983,
      "total_engagement": 310,
      "email_list_size": 1670,
      "tickets_sold_total": 0
    },
    {
      "date": "2026-03-22",
      "total_followers": 19539,
      "total_reach": 4164,
      "total_engagement": 323,
      "email_list_size": 1670,
      "tickets_sold_total": 0
    },
    {
      "date": "2026-03-23",
      "total_followers": 19957,
      "total_reach": 3921,
      "total_engagement": 292,
      "email_list_size": 1670,
      "tickets_sold_total": 0
    },
    {
      "date": "2026-03-24",
      "total_followers": 19993,
      "total_reach": 3679,
      "total_engagement": 292,
      "email_list_size": 1670,
      "tickets_sold_total": 0
    },
    {
      "date": "2026-03-29",
      "total_followers": 19765,
      "total_reach": 2371,
      "total_engagement": 118,
      "email_list_size": 1669,
      "tickets_sold_total": 0
    }
  ],
  "platform_status": {
    "instagram": "2026-04-03T01:10:23.494833+00:00",
    "spotify": null,
    "emailoctopus": "2026-04-01T15:00:36.296783+00:00",
    "twitter": null,
    "tiktok": null,
    "meta_ads": null,
    "web": null,
    "shows": null,
    "youtube": "2026-04-02T12:13:20.821016+00:00"
  }
}